cruscopoetry/plugins/cruscoarud/__init__.py
cruscopoetry/plugins/cruscoarud/__main__.py
cruscopoetry/plugins/cruscoarud/exceptions.py
cruscopoetry/plugins/cruscoarud/utils.py
cruscopoetry/plugins/cruscoarud/common/__init__.py
cruscopoetry/plugins/cruscoarud/common/configuration.py
cruscopoetry/plugins/cruscoarud/common/constants.toml
cruscopoetry/plugins/cruscoarud/common/exceptions.py
cruscopoetry/plugins/cruscoarud/common/foot_namer.py
cruscopoetry/plugins/cruscoarud/common/metric_elements.py
cruscopoetry/plugins/cruscoarud/common/elements/abstract/__init__.py
cruscopoetry/plugins/cruscoarud/common/elements/abstract/condition.py
cruscopoetry/plugins/cruscoarud/common/elements/abstract/transformation.py
cruscopoetry/plugins/cruscoarud/common/elements/cillas/__init__.py
cruscopoetry/plugins/cruscoarud/common/elements/cillas/cillas.py
cruscopoetry/plugins/cruscoarud/common/elements/daairas/__init__.py
cruscopoetry/plugins/cruscoarud/common/elements/daairas/daairas.py
cruscopoetry/plugins/cruscoarud/common/elements/feet/__init__.py
cruscopoetry/plugins/cruscoarud/common/elements/feet/feet.py
cruscopoetry/plugins/cruscoarud/common/elements/metre_forms/__init__.py
cruscopoetry/plugins/cruscoarud/common/elements/metre_forms/metre_forms.py
cruscopoetry/plugins/cruscoarud/common/elements/metres/__init__.py
cruscopoetry/plugins/cruscoarud/common/elements/metres/metres.py
cruscopoetry/plugins/cruscoarud/common/elements/zihaafas/__init__.py
cruscopoetry/plugins/cruscoarud/common/elements/zihaafas/zihaafas.py
cruscopoetry/plugins/cruscoarud/parser/__init__.py
cruscopoetry/plugins/cruscoarud/parser/cilla_parser.py
cruscopoetry/plugins/cruscoarud/parser/exceptions.py
cruscopoetry/plugins/cruscoarud/parser/foot_parser.py
cruscopoetry/plugins/cruscoarud/parser/hemistich_parser.py
cruscopoetry/plugins/cruscoarud/parser/line_parser.py
cruscopoetry/plugins/cruscoarud/parser/text_parser.py
cruscopoetry/plugins/cruscoarud/parser/zihaafa_parser.py
cruscopoetry.plugins.cruscoarud-0.0.2.dist-info/METADATA
cruscopoetry.plugins.cruscoarud-0.0.2.dist-info/WHEEL
cruscopoetry.plugins.cruscoarud-0.0.2.dist-info/entry_points.txt
cruscopoetry.plugins.cruscoarud-0.0.2.dist-info/top_level.txt
cruscopoetry.plugins.cruscoarud-0.0.2.dist-info/RECORD
