Metadata-Version: 2.1
Name: cruscopoetry.plugins.cruscoarud
Version: 0.0.2
Summary: ʿArūḍ parser for poems in cruscopoetry format
Home-page: https://gitlab.com/kikulacho92/cruscopoetry_new
Author: Emiliano Minerba
Author-email: emi.nerba@gmail.com
License: GPL
Platform: UNKNOWN
Requires-Dist: cruscopoetry.core
Requires-Dist: cruscopoetry.plugins.abstract
Requires-Dist: myusefulclasses
Requires-Dist: myusefulmetaclasses
Requires-Dist: tomli
